ocrd_ocropy/__init__.py
ocrd_ocropy/cli.py
ocrd_ocropy/config.py
ocrd_ocropy/ocrd-tool.json
ocrd_ocropy/segment.py
ocrd_ocropy-0.0.3.dist-info/LICENSE
ocrd_ocropy-0.0.3.dist-info/METADATA
ocrd_ocropy-0.0.3.dist-info/WHEEL
ocrd_ocropy-0.0.3.dist-info/entry_points.txt
ocrd_ocropy-0.0.3.dist-info/top_level.txt
ocrd_ocropy-0.0.3.dist-info/RECORD
