Metadata-Version: 2.1
Name: ocrd-ocropy
Version: 0.0.3
Summary: ocropy bindings
Home-page: https://github.com/OCR-D/ocrd_ocropy
Author: Konstantin Baierer
Author-email: unixprog@gmail.com, wuerzner@gmail.com
License: Apache License 2.0
Platform: UNKNOWN
Requires-Dist: ocrd (>=1.0.0b8)
Requires-Dist: ocrd-fork-ocropy (>=1.4.0a3)
Requires-Dist: click
